<?xml version="1.0" encoding="UTF-8"?>
<territory>
    <id>chile</id>
    <short-form-name>Chile</short-form-name>
    <long-form-name>Republic of Chile</long-form-name>
    <type-of-territory>independent-state</type-of-territory>
    <valid-since>1810</valid-since>
    <valid-until>9999</valid-until>
    <exists-on-todays-map>true</exists-on-todays-map>
    <predecessors>
        <predecessor>viceroyalty-of-peru-1824</predecessor>
    </predecessors>
    <successors/>
    <notes>U.S. recognized independence in 1823</notes>
    <sources>
        <source>https://www.cia.gov/library/publications/the-world-factbook/geos/ci.html</source>
        <source>http://history.state.gov/countries/chile</source>
        <source>http://www.britannica.com/EBchecked/topic/453253/Viceroyalty-of-Peru</source>
    </sources>
</territory>