<?xml version="1.0" encoding="UTF-8"?>
<territory>
    <id>formosa-1683</id>
    <short-form-name>Formosa</short-form-name>
    <long-form-name>Ilha Formosa</long-form-name>
    <type-of-territory>dependency-or-area-of-special-sovereignty</type-of-territory>
    <valid-since>1590</valid-since>
    <valid-until>1683</valid-until>
    <exists-on-todays-map>false</exists-on-todays-map>
    <predecessors/>
    <successors>
        <successor>china-1912</successor>
    </successors>
    <notes/>
    <sources>
        <source>https://www.cia.gov/library/publications/the-world-factbook/geos/tw.html</source>
        <source>http://www.britannica.com/EBchecked/topic/580902/Taiwan/30027/Cultural-life#toc214552</source>
        <source>http://academic.eb.com.proxy.lib.umich.edu/EBchecked/topic/580902/Taiwan</source>
        <source>http://academic.eb.com.proxy.lib.umich.edu/EBchecked/topic/111803/China</source>
    </sources>
</territory>